{
  "listin": [
    {
      "t": "25019",
      "list": 1,
      "cat": 1,
      "subcat": 1,
      "status": 2,
      "title": "Primeiros passos no fórum",
      "desc": "Conselhos agrupados desde a criação do fórum até a sua atividade para ter um fórum ativo!"
    },
    {
      "t": "93907",
      "list": 1,
      "cat": 1,
      "subcat": 1,
      "status": 1,
      "title": "Aumente a segurança do fórum",
      "desc": "Sabia que é possível ter controle do fórum através do Painel administrativo? E existe riscos a quem dá acesso!"
    },
    {
      "t": "112365",
      "list": 1,
      "cat": 1,
      "subcat": 1,
      "title": "Benefícios de um fórum",
      "desc": "Crie um fórum grátis facilmente e desfrutar de muitos recursos e personalizações para ter um fórum único."
    },
    {
      "t": "102551",
      "list": 1,
      "cat": 1,
      "subcat": 1,
      "title": "Mensagens de problemas técnicos nos fóruns",
      "desc": "Apresentação das várias mensagens de erro técnicas nos fóruns."
    },
    {
      "t": "93381",
      "list": 1,
      "cat": 1,
      "subcat": 1,
      "title": "Recuperação ou Transferência de uma Conta Fundadora",
      "desc": "Perda da palavra-passe, recuperação ou backup do fórum"
    },
    {
      "t": "21652",
      "list": 1,
      "cat": 1,
      "subcat": 1,
      "title": "Registo da atividade do Administrador e Moderador",
      "desc": "Apresentação das várias mensagens de erro técnicas nos fóruns."
    },
    {
      "t": "118067",
      "list": 1,
      "cat": 1,
      "subcat": 2,
      "title": "Ferramentas do Fundador-administrador",
      "desc": "As ferramentas do fundador dão acesso remoto a gestão da sua comunidade."
    },
    {
      "t": "118091",
      "list": 1,
      "cat": 1,
      "subcat": 2,
      "title": "Os administradores",
      "desc": "Administradores são os membros com poder absoluto no fórum como a capacidade de aceder e executar ações dentro do painel administrativo."
    },
    {
      "t": "118093",
      "list": 1,
      "cat": 1,
      "subcat": 2,
      "title": "Permissões especiais",
      "desc": "Permissões especiais são restrições de acesso aos quatro principais grupos de membros do fórum. Ao selecionar um grupo a uma opção está a tirar o acesso de visualização."
    },
    {
      "t": "70923",
      "list": 1,
      "cat": 1,
      "subcat": 3,
      "title": "Pirataria nos fóruns",
      "desc": "Muitas vezes nos é questionado sobre o assunto da pirataria. O que é? O que pode acarretar? O que é tão importante para mantemos nossos fóruns legais? Isso é o que essa FAQ lhe explicará."
    },
    {
      "t": "92678",
      "list": 1,
      "cat": 1,
      "subcat": 3,
      "title": "Página AdFly ou domínio inacessível",
      "desc": " Existem 4 casos que podem ocasionar a inexistência dum domínio."
    },
    {
      "t": "30419",
      "list": 1,
      "cat": 1,
      "subcat": 3,
      "title": "Conteúdos ilícitos nos Fóruns Forumeiros",
      "desc": "Os conteúdos ilegais que estão presentes em um fórum desrespeitam as condições gerais de uso podem penalizá-lo. Aqui tem algumas dicas de como fiscalizar a sua comunidade."
    },
    {
      "t": "5209",
      "list": 1,
      "cat": 1,
      "subcat": 3,
      "title": "Serviço de litígios x Serviço de queixas",
      "desc": "Compreenda as diferenças entre ambos os serviços e quando cada um deles deve ser utilizado!"
    },
    {
      "t": "89473",
      "list": 1,
      "cat": 1,
      "subcat": 3,
      "title": "Online Guardian",
      "desc": "Você já acessou seu fórum e do nada um aviso dado pelo site OnlineGuardian foi exibido? O que deve-se fazer quando um fórum não existe mais e a informação do Online Guardian é exibido? - Vamos esclarecer sua dúvida a respeito disso. "
    },
    {
      "t": "98385",
      "list": 1,
      "cat": 1,
      "subcat": 3,
      "title": "Sobre Direitos Autorais",
      "desc": "Aprenda a usar o Copyright, seus direitos autorais, na defesa de seu fórum."
    },
    {
      "t": "93961",
      "list": 1,
      "cat": 2,
      "title": "Escolher um nome para o fórum",
      "desc": "Responsável por grande parte da construção da identidade do espaço de discussão e será uma marca do seu trabalho enquanto administrador."
    },
    {
      "t": "20132",
      "list": 1,
      "cat": 2,
      "title": "Gerir a descrição e título do fórum",
      "desc": "Através da descrição do fórum poderá atribuir a sua comunidade o tema simplificado do fórum para que os visitantes vejam."
    },
    {
      "t": "27132",
      "list": 1,
      "cat": 2,
      "title": "Convidar amigos",
      "desc": "Convide vários amigos a participar no fórum com poucos cliques."
    },
    {
      "t": "17785",
      "list": 1,
      "cat": 2,
      "title": "Ganhar mais visitas no fórum",
      "desc": "Publicitar um fórum é o melhor modo para fazê-lo ser reconhecido e com isso atrair mais visitas."
    },
    {
      "t": "30444",
      "list": 1,
      "cat": 2,
      "title": "O Diretório dos Fóruns",
      "desc": "É uma ferramenta de busca eficiente, que lhe permite encontrar o Fórum dos seus sonhos ou uma informação dentre todos os fóruns de Forumeiros."
    },
    {
      "t": "17786",
      "list": 1,
      "cat": 2,
      "title": "Divulgação do fórum",
      "desc": "O Banner é uma das imagens mais importantes que um fórum necessita ter. Apartir dela pode-se firmar parcerias."
    },
    {
      "t": "107876",
      "list": 1,
      "cat": 2,
      "title": "Ative o certificado SSL: Guia para uma passagem bem-sucedida do fórum em HTTPS",
      "desc": "Um guia com as diferentes informações e etapas a seguir para mudar o seu fórum para HTTPS."
    },
    {
      "t": "39787",
      "list": 1,
      "cat": 2,
      "title": "Melhorar o SEO do fórum",
      "desc": "Etapas para melhorar a busca do fórum nos motores de busca."
    },
    {
      "t": "21033",
      "list": 1,
      "cat": 2,
      "title": "Adicionar código \"Google Analytics\"",
      "desc": "O Google Analytics é a solução de análise da web de cunho empresarial que fornece a você uma ótima visibilidade do tráfego e da eficiência do marketing do seu website."
    },
    {
      "t": "96165",
      "list": 1,
      "title": "O meu fórum sofre uma penalidade do Google",
      "cat": 2,
      "desc": "Uma perda de visitas no seu fórum, ou uma diminuição de posição nas páginas de resultados do Google?"
    },
    {
      "t": "44898",
      "list": 1,
      "title": "Troca de tráfego",
      "cat": 2,
      "desc": "Aumente o SEO com a interligação dos tópicos semelhantes dos fóruns Forumeiros."
    },
    {
      "t": "21150",
      "list": 1,
      "title": "Compartilhar um tópico",
      "cat": 2,
      "desc": "Em todos os tópicos do fórum agora aparece um novo link \"Compartilhar\", que abre um menu que lista todas as suas redes sociais favoritas. (54 serviços)"
    },
    {
      "t": "17182",
      "list": 1,
      "cat": 3,
      "subcat": 1,
      "title": "Excluir um Fórum",
      "desc": "-"
    },
    {
      "t": "22688",
      "list": 1,
      "cat": 3,
      "subcat": 1,
      "title": "Redirecionar um domínio para um fórum",
      "desc": "-"
    },
    {
      "t": "34199",
      "list": 1,
      "cat": 3,
      "subcat": 1,
      "title": "Segurança em Forumeiros",
      "desc": "-"
    },
    {
      "t": "115350",
      "list": 1,
      "cat": 3,
      "subcat": 1,
      "title": "Suprimindo e restaurando um fórum",
      "desc": "A supressão de um fórum o tornará inacessível permanentemente (Condições implícitas no conteúdo da FAQ)."
    },
    {
      "t": "23026",
      "list": 1,
      "cat": 3,
      "subcat": 1,
      "title": "Ativar/desativar supressão de cookies",
      "desc": "Cookies são arquivos que contem informações de páginas da internet, tanto pode ser informações de login ou de sessão."
    },
    {
      "t": "17751",
      "list": 1,
      "cat": 3,
      "subcat": 1,
      "title": "Utilizar as Ferramentas de Usuários",
      "desc": "-"
    },
    {
      "t": "45096",
      "list": 1,
      "cat": 3,
      "subcat": 1,
      "title": "Vínculos externos, anti-spam",
      "desc": "-"
    },
    {
      "t": "16003",
      "list": 1,
      "cat": 3,
      "subcat": 1,
      "title": "Gestão das estatísticas do fórum",
      "desc": "-"
    },
    {
      "t": "9293",
      "list": 1,
      "cat": 3,
      "subcat": 1,
      "title": "Censura de palavras",
      "desc": "Aprenda"
    },
    {
      "t": "108992",
      "list": 1,
      "cat": 3,
      "subcat": 2,
      "title": "Ativar e gerenciar as \"Publicações\" no fórum",
      "desc": "-"
    },
    {
      "t": "90299",
      "list": 1,
      "cat": 3,
      "subcat": 2,
      "title": "Ativar botão \"Curtir\" em tópicos",
      "desc": "-"
    },
    {
      "t": "1297",
      "list": 1,
      "cat": 3,
      "subcat": 2,
      "title": "Administração e instalação do portal / widgets",
      "desc": "-"
    },
    {
      "t": "9192",
      "list": 1,
      "cat": 3,
      "subcat": 2,
      "title": "Ativação do Chatbox do fórum",
      "desc": "-"
    },
    {
      "t": "30566",
      "list": 1,
      "cat": 3,
      "subcat": 2,
      "title": "Ativar conexão com Facebook Connect",
      "desc": "-"
    },
    {
      "t": "114324",
      "list": 1,
      "cat": 3,
      "subcat": 2,
      "title": "Configurar o progressive web app (PWA) no fórum",
      "desc": "-"
    },
    {
      "t": "1315",
      "list": 1,
      "cat": 3,
      "subcat": 2,
      "title": "Calendário",
      "desc": "-"
    },
    {
      "t": "109343",
      "list": 1,
      "cat": 3,
      "subcat": 2,
      "title": "Criação e gerenciamento dos Eventos do fórum",
      "desc": "-"
    },
    {
      "t": "7164",
      "list": 1,
      "cat": 3,
      "subcat": 2,
      "title": "Criar votação/enquete e adicionar ao Portal",
      "desc": "-"
    },
    {
      "t": "15885",
      "list": 1,
      "cat": 3,
      "subcat": 2,
      "title": "Gerenciar os Widgets do Fórum",
      "desc": "-"
    },
    {
      "t": "22448",
      "list": 1,
      "cat": 3,
      "subcat": 2,
      "title": "Gestão do widget \"Palavras-chave\"",
      "desc": "-"
    },
    {
      "t": "22904",
      "list": 1,
      "cat": 3,
      "subcat": 2,
      "title": "Gestão do widget \"Novidades\"",
      "desc": "-"
    },
    {
      "t": "2010",
      "list": 1,
      "cat": 3,
      "subcat": 2,
      "title": "Gerir a galeria do fórum",
      "desc": "-"
    },
    {
      "t": "829",
      "list": 1,
      "cat": 3,
      "subcat": 2,
      "title": "Gerir as Fichas de personagem e o Módulo RPG",
      "desc": "-"
    },
    {
      "t": "16946",
      "list": 1,
      "cat": 3,
      "subcat": 2,
      "title": "Gerir a função \"Lançar dados\"",
      "desc": "-"
    },
    {
      "t": "13951",
      "list": 1,
      "cat": 3,
      "subcat": 2,
      "title": "Gestão do sistema de reputação / Botão obrigado",
      "desc": "-"
    },
    {
      "t": "14012",
      "list": 1,
      "cat": 3,
      "subcat": 2,
      "title": "Gerir o Sistema de pontos",
      "desc": "-"
    },
    {
      "t": "42976",
      "list": 1,
      "cat": 3,
      "subcat": 2,
      "title": "Gestão das páginas .JS (javascript)",
      "desc": "-"
    },
    {
      "t": "100134",
      "list": 1,
      "cat": 3,
      "subcat": 2,
      "title": "Interagir fórum com Redes Sociais",
      "desc": "-"
    },
    {
      "t": "7967",
      "list": 1,
      "cat": 3,
      "subcat": 2,
      "title": "Página HTML personalizada",
      "desc": "-"
    },
    {
      "t": "114436",
      "list": 1,
      "cat": 3,
      "subcat": 3,
      "title": "Redigir e enviar uma notificação push personalizada",
      "desc": "-"
    },
    {
      "t": "8479",
      "list": 1,
      "cat": 3,
      "subcat": 3,
      "title": "Adicionar ícones de mensagens",
      "desc": "-"
    },
    {
      "t": "17151",
      "list": 1,
      "cat": 3,
      "subcat": 3,
      "title": "Ativar a caixa de \"Resposta rápida\"",
      "desc": "-"
    },
    {
      "t": "13791",
      "list": 1,
      "cat": 3,
      "subcat": 3,
      "title": "Anúncios rotativos",
      "desc": "-"
    },
    {
      "t": "22335",
      "list": 1,
      "cat": 3,
      "subcat": 3,
      "title": "Colorir o título dos tópicos",
      "desc": "-"
    },
    {
      "t": "384",
      "list": 1,
      "cat": 3,
      "subcat": 3,
      "title": "Caixa de edição de mensagens",
      "desc": "-"
    },
    {
      "t": "14076",
      "list": 1,
      "cat": 3,
      "subcat": 3,
      "title": "Criar e gerir as Mensagens Privadas",
      "desc": "-"
    },
    {
      "t": "16404",
      "list": 1,
      "cat": 3,
      "subcat": 3,
      "title": "Criar mensagem (MP) de boas-vindas",
      "desc": "-"
    },
    {
      "t": "16446",
      "list": 1,
      "cat": 3,
      "subcat": 3,
      "title": "Configurar a ferramenta \"Fale conosco\"",
      "desc": "-"
    },
    {
      "t": "12427",
      "list": 1,
      "cat": 3,
      "subcat": 3,
      "title": "Como criar e gerir os Smileys",
      "desc": "-"
    },
    {
      "t": "17210",
      "list": 1,
      "cat": 3,
      "subcat": 3,
      "title": "Criar e gerir a mensagem na Home Page",
      "desc": "-"
    },
    {
      "t": "16777",
      "list": 1,
      "cat": 3,
      "subcat": 3,
      "title": "Criar uma caixa de entrada para seus e-mails",
      "desc": "-"
    },
    {
      "t": "9649",
      "list": 1,
      "cat": 3,
      "subcat": 3,
      "title": "Fixar / anunciar um tópico e personalizar post-it e anúncio",
      "desc": "-"
    },
    {
      "t": "8470",
      "list": 1,
      "cat": 3,
      "subcat": 3,
      "title": "Ferramentas de Moderação",
      "desc": "-"
    },
    {
      "t": "95433",
      "list": 1,
      "cat": 3,
      "subcat": 3,
      "title": "Gerenciamento do BBcode H2, H3 e H4",
      "desc": "-"
    },
    {
      "t": "27247",
      "list": 1,
      "cat": 3,
      "subcat": 3,
      "title": "Gerir a função de anexar arquivos (anexos)",
      "desc": "-"
    },
    {
      "t": "21090",
      "list": 1,
      "cat": 3,
      "subcat": 3,
      "title": "Inserir descrição em tópicos",
      "desc": "-"
    },
    {
      "t": "26579",
      "list": 1,
      "cat": 3,
      "subcat": 3,
      "title": "Limitar o número de citações numa mensagem",
      "desc": "-"
    },
    {
      "t": "13842",
      "list": 1,
      "cat": 3,
      "subcat": 3,
      "title": "Multi citação",
      "desc": "-"
    },
    {
      "t": "21858",
      "list": 1,
      "cat": 3,
      "subcat": 3,
      "title": "Permitir / Proibir a mudança do título dos tópicos",
      "desc": "-"
    },
    {
      "t": "7165",
      "list": 1,
      "cat": 3,
      "subcat": 3,
      "title": "Redigir e enviar uma newsletter ou e-mail em massa",
      "desc": "-"
    },
    {
      "t": "99009",
      "list": 1,
      "cat": 3,
      "subcat": 3,
      "title": "Redigir e enviar uma Mensagem Privada (MP) em massa",
      "desc": "-"
    },
    {
      "t": "9444",
      "list": 1,
      "cat": 3,
      "subcat": 3,
      "title": "Relatório de alerta",
      "desc": "-"
    },
    {
      "t": "26431",
      "list": 1,
      "cat": 3,
      "subcat": 3,
      "title": "Redimensionamento de imagens",
      "desc": "-"
    },
    {
      "t": "13925",
      "list": 1,
      "cat": 3,
      "subcat": 3,
      "title": "Sistema anti-flood",
      "desc": "-"
    },
    {
      "t": "22211",
      "list": 1,
      "cat": 3,
      "subcat": 3,
      "title": "Tempo limite para editar uma mensagem",
      "desc": "-"
    },
    {
      "t": "27207",
      "list": 1,
      "cat": 3,
      "subcat": 3,
      "title": "Tópicos especiais: Anúncio global",
      "desc": "-"
    },
    {
      "t": "27813",
      "list": 1,
      "cat": 3,
      "subcat": 3,
      "title": "Utilização de spoilers",
      "desc": "-"
    },
    {
      "t": "30498",
      "list": 1,
      "cat": 3,
      "subcat": 3,
      "title": "Visualizar o botão resolvido",
      "desc": "-"
    },
    {
      "t": "9204",
      "list": 1,
      "cat": 3,
      "subcat": 3,
      "title": "Variáveis",
      "desc": "-"
    },
    {
      "t": "16564",
      "list": 1,
      "cat": 3,
      "subcat": 3,
      "title": "Configurações do e-mail do fórum",
      "desc": "-"
    },
    {
      "t": "93909",
      "list": 1,
      "cat": 3,
      "subcat": 3,
      "title": "Gerenciar categorias para suas imagens Servimg",
      "desc": "-"
    },
    {
      "t": "20351",
      "list": 1,
      "cat": 3,
      "subcat": 3,
      "title": "Utilizar o Servimg",
      "desc": "-"
    },
    {
      "t": "16253",
      "list": 1,
      "cat": 4,
      "subcat": 1,
      "title": "Gestão dos usuários",
      "desc": "Pode gerenciar os seus membros ativos ou não, advertindo-os por e-mail sobre a sua inatividade podendo excluindo-os ou desativar."
    },
    {
      "t": "17340",
      "list": 1,
      "cat": 4,
      "subcat": 1,
      "title": "Ativar novos membros",
      "desc": "Quando um membro novo registra-se no Fórum, a conta pode ser ativada por e-mail, pelo administrador do fórum ou ativada automaticamente, dando a escolha ao administrador."
    },
    {
      "t": "14811",
      "list": 1,
      "cat": 4,
      "subcat": 1,
      "title": "Permitir assinaturas e suas permissões",
      "desc": "Uma assinatura é uma mensagem personalizada que é exibida abaixo de cada mensagem do publicador. Como configurá-lo?"
    },
    {
      "t": "25756",
      "list": 1,
      "cat": 4,
      "subcat": 1,
      "title": "Cancelamento da inscrição",
      "desc": "Às vezes, por diversos motivo, os membros do fórum preferem apagar a sua conta no fórum."
    },
    {
      "t": "93962",
      "list": 1,
      "cat": 4,
      "subcat": 1,
      "title": "Gestão de banimentos",
      "desc": "Aprenda como gerenciar o banimento do membro do fórum."
    },
    {
      "t": "9293",
      "list": 1,
      "cat": 4,
      "subcat": 1,
      "title": "Censura de nomes de usuário",
      "desc": "Aprenda a bloquear nomes de usuário ao registrar do fórum."
    },
    {
      "t": "15419",
      "list": 1,
      "cat": 4,
      "subcat": 1,
      "title": "Escolha e configuração de avatares",
      "desc": "Quando regista-se em um fórum, tem a opção de adicionar um avatar no seu perfil."
    },
    {
      "t": "22010",
      "list": 1,
      "cat": 4,
      "subcat": 1,
      "title": "Gestão de aniversários",
      "desc": "O gerenciamento de aniversários oferece opções para comemorar os aniversários dos membros do fórum."
    },
    {
      "t": "26525",
      "list": 1,
      "cat": 4,
      "subcat": 1,
      "title": "Tempo limite para o membro ser considerado como \"Offline\"",
      "desc": "Esta opção permite definir o tempo em minutos em que um membro é considerado \"offline\" se não tiver em atividade."
    },
    {
      "t": "12839",
      "list": 1,
      "cat": 4,
      "subcat": 2,
      "title": "Os grupos",
      "desc": "Este tutorial explica como criar um grupo, personalizá-lo e como ele funciona, para que você possa gerenciar os seus grupos facilmente."
    },
    {
      "t": "9077",
      "list": 1,
      "cat": 4,
      "subcat": 2,
      "title": "Classificação (ranks)",
      "desc": "Como criar uma classificação? O que é uma classificação especial? Como atribuir uma classificação? Como personalizar uma classificação? Todas essas questões são respondidas neste tópico."
    },
    {
      "t": "18896",
      "list": 1,
      "cat": 4,
      "subcat": 3,
      "title": "Posição do perfil nas mensagens (exceto em PhpBB2)",
      "desc": "Permite que você coloque seus perfis à direita ou à esquerda nos tópicos."
    },
    {
      "t": "14012",
      "list": 1,
      "cat": 4,
      "subcat": 3,
      "title": "Sistema de pontos",
      "desc": "O sistema de pontos permite atribuir pontos aos membros de acordo com o número de mensagens, data de inscrição, etc."
    },
    {
      "t": "118068",
      "list": 1,
      "cat": 4,
      "subcat": 3,
      "title": "Sistema de conquistas",
      "desc": "As conquistas são como troféus. Recompensas desbloqueadas ao alcançar um determinado valor em uma determinada área."
    },
    {
      "t": "17049",
      "list": 1,
      "cat": 4,
      "subcat": 3,
      "title": "Gestão de campos de perfil",
      "desc": "Este tutorial explica como alterar os campos de perfil, adaptados com o perfil avançado."
    },
    {
      "t": "829",
      "list": 1,
      "cat": 4,
      "subcat": 3,
      "title": "Gestão da Ficha de personagem e o Módulo RPG",
      "desc": "Este tutorial detalha o procedimento para ativar e configurar uma folha de personagem."
    },
    {
      "t": "25528",
      "list": 1,
      "cat": 4,
      "subcat": 4,
      "title": "Permitir que moderadores vejam membros invisíveis",
      "desc": "Por vezes, é proveitoso que os \"moderadores\" possam visualizar os membros invisíveis do fórum, agora verá como pode permitir a utilização desta ferramenta."
    },
    {
      "t": "27025",
      "list": 1,
      "cat": 4,
      "subcat": 4,
      "title": "Permissão para ver o IP do membro numa mensagem",
      "desc": "Escolha o nível de permissão de quem pode ver o IP de quem publicou."
    },
    {
      "t": "20078",
      "list": 1,
      "cat": 4,
      "subcat": 4,
      "title": "Permitir que moderadores possam banir um membro",
      "desc": "Escolha se quer ou não que os moderadores do fórum possam banir membros."
    },
    {
      "t": "20324",
      "list": 1,
      "cat": 4,
      "subcat": 4,
      "title": "Desativar o envio de uma nova senha para administradores e moderadores",
      "desc": "Esta opção desativa o uso do 'Esqueci-me da senha' para administradores e moderadores."
    },
    {
      "t": "8470",
      "list": 1,
      "cat": 4,
      "subcat": 4,
      "title": "Moderadores: Como moderar",
      "desc": "Uma ferramenta para moderar o fórum eficazmente."
    },
    {
      "t": "15664",
      "list": 1,
      "cat": 4,
      "subcat": 1,
      "title": "Alterar o logo do Fórum",
      "desc": "Aprenda a alterar o logotipo do fórum para o seu."
    },
    {
      "t": "49309",
      "list": 1,
      "cat": 4,
      "subcat": 1,
      "title": "A folha de estilo CSS",
      "desc": "Graças à folha CSS, tens a possibilidade de personalizar a exibição do seu fórum Forumeiros."
    },
    {
      "t": "2156",
      "list": 1,
      "cat": 4,
      "subcat": 1,
      "title": "As cores",
      "desc": "Todas as cores são configuráveis, e este tutorial agrupa todos os lugares onde as escolhas do painel de administração atuam."
    },
    {
      "t": "16480",
      "list": 1,
      "cat": 4,
      "subcat": 1,
      "title": "Temas temporários",
      "desc": "O que são temas temporários e como usá-los?"
    },
    {
      "t": "16113",
      "list": 1,
      "cat": 4,
      "subcat": 1,
      "title": "Exportar e importar um tema",
      "desc": "Este tutorial explica como exportar e importar seu tema."
    },
    {
      "t": "15900",
      "list": 1,
      "cat": 4,
      "subcat": 1,
      "title": "Versões do fórum",
      "desc": "Este tutorial apresentará as diferentes versões oferecidas pelo Forumeiros, como reconhecê-las e alterá-las no seu fórum"
    },
    {
      "t": "20295",
      "list": 1,
      "cat": 4,
      "subcat": 1,
      "title": "Ícones de mensagens",
      "desc": "Os ícones de mensagem são imagens pequenas que ilustram - por exemplo - o estado do autor ou o status da mensagens."
    },
    {
      "t": "16827",
      "list": 1,
      "cat": 4,
      "subcat": 2,
      "title": "Modifique os templates do fórum",
      "desc": "O que são templates? Quem pode e como modificar os templates do fórum? Todas as resposta estão aqui."
    },
    {
      "t": "8652",
      "list": 1,
      "cat": 4,
      "subcat": 3,
      "title": "Buscar um tema em HitSkin.com",
      "desc": "-"
    },
    {
      "t": "17239",
      "list": 1,
      "cat": 4,
      "subcat": 3,
      "title": "Criar uma conta em Hitskin.com",
      "desc": "-"
    },
    {
      "t": "17311",
      "list": 1,
      "cat": 4,
      "subcat": 3,
      "title": "Propor um tema em Hitskin.com",
      "desc": "-"
    },
    {
      "t": "17276",
      "list": 1,
      "cat": 4,
      "subcat": 3,
      "title": "Instalar / criar um fórum com um tema do HitSkin",
      "desc": "-"
    }
  ],
  "topic_count": 624
}
